README.md
setup.py
mydb_tsm/__init__.py
mydb_tsm/mydb_tsm.py
mydb_tsm/test.py
mydb_tsm.egg-info/PKG-INFO
mydb_tsm.egg-info/SOURCES.txt
mydb_tsm.egg-info/dependency_links.txt
mydb_tsm.egg-info/top_level.txt