Metadata-Version: 2.1
Name: mydb-tsm
Version: 1.0.1
Author: Tomboy
Author-email: Tomboy1996@163.com
